Ejercicio_5/Ejercicio_5.v
/* Margareth Vela
Carné: 19458

Memoria ROM*/

module ROM (input wire [6:0]Address, output reg [12:0]Y);
  always @(Address) begin
    casex(Address)
      7'bxxxxxx0: Y = 13'b1000000001000 ;//caso 1
      7'b00001x1: Y = 13'b0100000001000 ;//caso 2
      7'b00000x1: Y = 13'b1000000001000 ;//caso 3
      7'b00011x1: Y = 13'b1000000001000 ;//caso 4
      7'b00010x1: Y = 13'b0100000001000 ;//caso 5
      7'b0010xx1: Y = 13'b0001001000010 ;//caso 6
      7'b0011xx1: Y = 13'b1001001100000 ;//caso 7
      7'b0100xx1: Y = 13'b0011010000010 ;//caso 8
      7'b0101xx1: Y = 13'b0011010000100 ;//Caso 9
      7'b0110xx1: Y = 13'b1011010100000 ;//caso 10
      7'b0111xx1: Y = 13'b1000000111000 ;//caso 11
      7'b1000x11: Y = 13'b0100000001000 ;//caso 12
      7'b1000x01: Y = 13'b1000000001000 ;//caso 13
      7'b1001x11: Y = 13'b1000000001000 ;//caso 14
      7'b1001x01: Y = 13'b0100000001000 ;//caso 15
      7'b1010xx1: Y = 13'b0011011000010 ;//caso 16
      7'b1011xx1: Y = 13'b1011011100000 ;//caso 17
      7'b1100xx1: Y = 13'b0100000001000 ;//caso 18
      7'b1101xx1: Y = 13'b0000000001001 ;//caso 19
      7'b1110xx1: Y = 13'b0011100000010 ;//caso 20
      7'b1111xx1: Y = 13'b1011100100000 ;//caso 21
      default:    Y = 13'b0 ; // caso por default
    endcase
  end

endmodule

Ejercicio_5/testbench_tb.v
//Testbench ejercicio 5
module testbench ();
    reg [6:0]ADDRESS;
    wire [12:0]Y;

    ROM G1(ADDRESS,Y);

    initial begin
        $display("\n");
        $display(" MEMORIA ROM - Ejercicio 5");
        $display("ADDRESS |       Y");
        $monitor("%b | %b ", ADDRESS, Y );
        #1 ADDRESS = 7'b0000000;//caso 1
        #1 ADDRESS = 7'b0100000;//caso 1
        #1 ADDRESS = 7'b1000000;//caso 1
        #1 ADDRESS = 7'b0000010;//caso 1
        #1 ADDRESS = 7'b1111110;//caso 1
        #1 ADDRESS = 7'b0000101;//caso 2
        #1 ADDRESS = 7'b0000011;//caso 3
        #1 ADDRESS = 7'b0001101;//caso 4
        #1 ADDRESS = 7'b0001011;//caso 5
        #1 ADDRESS = 7'b0010011;//caso 6
        #1 ADDRESS = 7'b0011001;//caso 7
        #1 ADDRESS = 7'b0100101;//caso 8
        #1 ADDRESS = 7'b0101101;//caso 9
        #1 ADDRESS = 7'b0110011;//caso 10
        #1 ADDRESS = 7'b0111001;//caso 11
        #1 ADDRESS = 7'b1000111;//caso 12
        #1 ADDRESS = 7'b0000001;//caso 13
        #1 ADDRESS = 7'b1001111;//caso 14
        #1 ADDRESS = 7'b1001001;//caso 15
        #1 ADDRESS = 7'b1010001;//caso 16
        #1 ADDRESS = 7'b1011011;//caso 17
        #1 ADDRESS = 7'b1100001;//caso 18
        #1 ADDRESS = 7'b1101001;//caso 19
        #1 ADDRESS = 7'b1110111;//caso 20
        #1 ADDRESS = 7'b1111111;//caso 21
        #1 ADDRESS = 7'b0011111;//caso 7
        #1 ADDRESS = 7'b0110111;//caso 10
        #1 ADDRESS = 7'b0001111;//caso 4
        #1 ADDRESS = 7'b1001101;//caso 15
        #1 ADDRESS = 7'b1110011;//caso 20
        #1 ADDRESS = 7'b1111101;//caso 21
        #1 ADDRESS = 7'b1111100;//caso 1

        #1 $finish;
    end

    initial begin
          $dumpfile("testbench_tb.vcd");
          $dumpvars(0, testbench);
        end

endmodule

Ejercicio_5/ej05_tb.vcd
$date
	Sat Oct 31 09:34:53 2020
$end
$version
	Icarus Verilog
$end
$timescale
	1ps
$end
$scope module testbench $end
$var wire 13 ! Y [12:0] $end
$var reg 7 " ADDRESS [6:0] $end
$scope module G1 $end
$var wire 7 # Address [6:0] $end
$var reg 13 $ Y [12:0] $end
$upscope $end
$upscope $end
$enddefinitions $end
#0
$dumpvars
bx $
bx #
bx "
bx !
$end
#2
b1000000001000 !
b1000000001000 $
b0 "
b0 #
#3
b100000 "
b100000 #
#4
b1000000 "
b1000000 #
#5
b10 "
b10 #
#6
b1111110 "
b1111110 #
#7
b100000001000 !
b100000001000 $
b101 "
b101 #
#8
b0 !
b0 $
b11 "
b11 #
#9
b1000000001000 !
b1000000001000 $
b1101 "
b1101 #
#10
b1001000010 !
b1001000010 $
b10011 "
b10011 #
#11
b1001001100000 !
b1001001100000 $
b11001 "
b11001 #
#12
b11010000100 !
b11010000100 $
b101101 "
b101101 #
#13
b11010000010 !
b11010000010 $
b100101 "
b100101 #
#14
b1011010100000 !
b1011010100000 $
b110011 "
b110011 #
#15
b1000000111000 !
b1000000111000 $
b111001 "
b111001 #
#16
b100000001000 !
b100000001000 $
b1000111 "
b1000111 #
#17
b1000000001000 !
b1000000001000 $
b1001111 "
b1001111 #
#18
b1 "
b1 #
#19
b100000001000 !
b100000001000 $
b1001001 "
b1001001 #
#20
b11011000010 !
b11011000010 $
b1010001 "
b1010001 #
#21
b1011011100000 !
b1011011100000 $
b1011011 "
b1011011 #
#22
b1011100100000 !
b1011100100000 $
b1111111 "
b1111111 #
#23
b11100000010 !
b11100000010 $
b1110111 "
b1110111 #
#24
b1001 !
b1001 $
b1101001 "
b1101001 #
#25
b100000001000 !
b100000001000 $
b1100001 "
b1100001 #
#26
b1001001100000 !
b1001001100000 $
b11111 "
b11111 #
#27
b1011010100000 !
b1011010100000 $
b110111 "
b110111 #
#28
b1000000001000 !
b1000000001000 $
b1111 "
b1111 #
#29
b100000001000 !
b100000001000 $
b1001101 "
b1001101 #
#30
b11100000010 !
b11100000010 $
b1110011 "
b1110011 #
#31
b1011100100000 !
b1011100100000 $
b1111101 "
b1111101 #
#32
b1000000001000 !
b1000000001000 $
b1111100 "
b1111100 #
