Ejercicio_1/Ejercicio_1.v
/* Margareth Vela
Carné: 19458

Ejercicio 1 - Flip Flop tipo D de 1 bit */

module FF_D1(input wire clock, reset, enable, d, output reg Y);
  always @ (posedge clock, posedge reset) begin
    if(reset) begin
      Y <= 1'b0;
    end
    else if (enable == 1) begin
      Y <= d;
    end
    else if (enable == 0) begin
      Y <= Y;
    end
  end
endmodule

//Flip Flop tipo D de 2 bits
module FF_D2(input wire clock, reset, enable, input wire [1:0] d, output wire [1:0] Y);
  FF_D1 G1(clock, reset, enable, d[1], Y[1]);
  FF_D1 G2(clock, reset, enable, d[0], Y[0]);
endmodule

//Flip Flop tipo D de 2 bits
module FF_D4(input wire clock, reset, enable, input wire [3:0] d, output wire [3:0] Y);
  FF_D1 G1(clock, reset, enable, d[3], Y[3]);
  FF_D1 G2(clock, reset, enable, d[2], Y[2]);
  FF_D1 G3(clock, reset, enable, d[1], Y[1]);
  FF_D1 G4(clock, reset, enable, d[0], Y[0]);
endmodule

Ejercicio_1/testbench_tb.v
//Testbench ejercicio 1
module testbench();

  reg clk, rst, enable, d;
  reg [1:0] d2;
  reg [3:0] d4;
  wire Y;
  wire [1:0] Y2;
  wire [3:0] Y4;

  FF_D1 U1(clk, rst, enable, d, Y);
  FF_D2 U2(clk, rst, enable, d2,Y2);
  FF_D4 U3(clk, rst, enable, d4, Y4);

  always
    begin
      clk <= 1;
      #1 clk <= ~clk;
      #1;
  end

  initial begin
  $display("\n");
    $display("Flip Flop de 1 bit - Ejercicio 1");
    $display("\n");
    $display(" Clk RST | EN    D |   Y    ");
    $display(" --------------------------- ");
    $monitor(" %b    %b  | %b     %b |   %b ", clk, rst, enable, d, Y);

    #1 rst = 1; //Reset inicial
    #1 rst = 0; //Reset inicial
    #2 enable = 1; d = 1;
    #2 d = 0;
    #2 d = 1;
    #2 enable = 0; d = 0;
    #2 d = 1;
    #2 enable = 1;
    #2 d = 0;
    end

  initial begin
  #18
  $display("\n");
    $display("Flip Flop de 2 bits - Ejercicio 1");
    $display("\n");
    $display(" Clk RST | EN     D |    Y    ");
    $display(" ---------------------------- ");
    $monitor(" %b    %b  | %b     %b |   %b ", clk, rst, enable, d2, Y2);

    #1 rst = 1; //Reset inicial
    #1 rst = 0; enable = 0; //Reset inicial
    #2 enable = 1; d2[1] = 0; d2[0] = 1;
    #2 d2[1] = 1; d2[0] = 0;
    #2 d2[1] = 0; d2[0] = 0;
    #2 enable = 0; d2[1] = 0; d2[0] = 1;
    #2 d2[1] = 1; d2[0] = 0;
    #2 enable = 1;
    #2 d2[1] = 1; d2[0] = 1;
    end

    initial begin
    #36
    $display("\n");
      $display("Flip Flop de 4 bits - Ejercicio 1");
      $display("\n");
      $display(" Clk RST | EN     D   |    Y    ");
      $display(" ------------------------------- ");
      $monitor(" %b    %b  | %b     %b |   %b ", clk, rst, enable, d4, Y4);

      #1 rst = 1; //Reset inicial
      #1 rst = 0; enable = 0;//Reset inicial
      #2 enable = 1; d4[3] = 0; d4[2] = 0; d4[1] = 0; d4[0] = 1;
      #2 d4[3] = 0; d4[2] = 0; d4[1] = 0; d4[0] = 1;
      #2 d4[3] = 0; d4[2] = 0; d4[1] = 1; d4[0] = 1;
      #2 enable = 0; d4[3] = 1; d4[2] = 0; d4[1] = 1; d4[0] = 1;
      #2 d4[3] = 0; d4[2] = 1; d4[1] = 1; d4[0] = 1;
      #2 enable = 1;
      #2 d4[3] = 1; d4[2] = 1; d4[1] = 1; d4[0] = 1;
      #5 $finish;

      end

    initial begin
          $dumpfile("testbench_tb.vcd");
          $dumpvars(0, testbench);
        end
endmodule

Ejercicio_1/testbench_tb.vcd
$date
	Thu Oct 29 11:51:54 2020
$end
$version
	Icarus Verilog
$end
$timescale
	1ps
$end
$scope module testbench $end
$var wire 4 ! Y4 [3:0] $end
$var wire 2 " Y2 [1:0] $end
$var wire 1 # Y $end
$var reg 1 $ clk $end
$var reg 1 % d $end
$var reg 2 & d2 [1:0] $end
$var reg 4 ' d4 [3:0] $end
$var reg 1 ( enable $end
$var reg 1 ) rst $end
$scope module U1 $end
$var wire 1 $ clock $end
$var wire 1 % d $end
$var wire 1 ( enable $end
$var wire 1 ) reset $end
$var reg 1 # Y $end
$upscope $end
$scope module U2 $end
$var wire 1 $ clock $end
$var wire 2 * d [1:0] $end
$var wire 1 ( enable $end
$var wire 1 ) reset $end
$var wire 2 + Y [1:0] $end
$scope module G1 $end
$var wire 1 $ clock $end
$var wire 1 , d $end
$var wire 1 ( enable $end
$var wire 1 ) reset $end
$var reg 1 - Y $end
$upscope $end
$scope module G2 $end
$var wire 1 $ clock $end
$var wire 1 . d $end
$var wire 1 ( enable $end
$var wire 1 ) reset $end
$var reg 1 / Y $end
$upscope $end
$upscope $end
$scope module U3 $end
$var wire 1 $ clock $end
$var wire 4 0 d [3:0] $end
$var wire 1 ( enable $end
$var wire 1 ) reset $end
$var wire 4 1 Y [3:0] $end
$scope module G1 $end
$var wire 1 $ clock $end
$var wire 1 2 d $end
$var wire 1 ( enable $end
$var wire 1 ) reset $end
$var reg 1 3 Y $end
$upscope $end
$scope module G2 $end
$var wire 1 $ clock $end
$var wire 1 4 d $end
$var wire 1 ( enable $end
$var wire 1 ) reset $end
$var reg 1 5 Y $end
$upscope $end
$scope module G3 $end
$var wire 1 $ clock $end
$var wire 1 6 d $end
$var wire 1 ( enable $end
$var wire 1 ) reset $end
$var reg 1 7 Y $end
$upscope $end
$scope module G4 $end
$var wire 1 $ clock $end
$var wire 1 8 d $end
$var wire 1 ( enable $end
$var wire 1 ) reset $end
$var reg 1 9 Y $end
$upscope $end
$upscope $end
$upscope $end
$enddefinitions $end
#0
$dumpvars
x9
x8
x7
x6
x5
x4
x3
x2
bx 1
bx 0
x/
x.
x-
x,
bx +
bx *
x)
x(
bx '
bx &
x%
1$
x#
bx "
bx !
$end
#1
09
07
05
b0 !
b0 1
03
0/
b0 "
b0 +
0-
0#
0$
1)
#2
1$
0)
#3
0$
#4
x9
x7
x5
bx !
bx 1
x3
x/
bx "
bx +
x-
1#
1$
1%
1(
#5
0$
#6
0#
1$
0%
#7
0$
#8
1#
1$
1%
#9
0$
#10
1$
0%
0(
#11
0$
#12
1$
1%
#13
0$
#14
1$
1(
#15
0$
#16
0#
1$
0%
#17
0$
#18
1$
#19
09
07
05
b0 !
b0 1
03
0/
b0 "
b0 +
0-
0$
1)
#20
1$
0(
0)
#21
0$
#22
x9
x7
x5
bx !
bx 1
x3
b1 "
b1 +
1/
1$
1.
0,
b1 &
b1 *
1(
#23
0$
#24
1-
b10 "
b10 +
0/
1$
0.
1,
b10 &
b10 *
#25
0$
#26
b0 "
b0 +
0-
1$
0,
b0 &
b0 *
#27
0$
#28
1$
1.
b1 &
b1 *
0(
#29
0$
#30
1$
0.
1,
b10 &
b10 *
#31
0$
#32
b10 "
b10 +
1-
1$
1(
#33
0$
#34
b11 "
b11 +
1/
1$
1.
b11 &
b11 *
#35
0$
#36
1$
#37
09
07
05
b0 !
b0 1
03
0/
b0 "
b0 +
0-
0$
1)
#38
1$
0(
0)
#39
0$
#40
b1 !
b1 1
19
1/
b11 "
b11 +
1-
1$
18
06
04
02
b1 '
b1 0
1(
#41
0$
#42
1$
#43
0$
#44
b11 !
b11 1
17
1$
16
b11 '
b11 0
#45
0$
#46
1$
12
b1011 '
b1011 0
0(
#47
0$
#48
1$
14
02
b111 '
b111 0
#49
0$
#50
b111 !
b111 1
15
1$
1(
#51
0$
#52
b1111 !
b1111 1
13
1$
12
b1111 '
b1111 0
