Ejercicio_4/Ejercicio_4.v
/* Margareth Vela
Carné: 19458

Buffer de 4 bits*/

module Buffer_4(input wire enable, input wire [3:0]A, output wire [3:0] Y);
  assign Y = enable ? A : 4'bz;
endmodule

Ejercicio_4/testbench_tb.v
//Testbench ejercicio 4
module testbench();

  reg enable;
  reg [3:0] A;
  wire[3:0] Y;

  Buffer_4 B1(enable, A, Y);

  initial begin
    $display("\n");
      $display("Buffer Triestado - Ejercicio 4");
      $display("\n");
      $display(" Enable    A    |    Y    ");
      $display(" -----------------------");
      $monitor(" %b        %b  |   %b ", enable, A, Y);
      #1 enable = 1; A[0]=0; A[1]=1; A[2]=0; A[3]=0;
      #1 enable = 1; A[0]=0; A[1]=1; A[2]=1; A[3]=1;
      #1 enable = 1; A[0]=1; A[1]=1; A[2]=1; A[3]=1;
      #1 enable = 0; A[0]=1; A[1]=1; A[2]=0; A[3]=1;
      #1 enable = 1; A[0]=1; A[1]=0; A[2]=0; A[3]=0;
      #1 enable = 0; A[0]=0; A[1]=1; A[2]=0; A[3]=1;
      #1 enable = 1; A[0]=1; A[1]=0; A[2]=1; A[3]=0;
      #1 enable = 1; A[0]=1; A[1]=0; A[2]=1; A[3]=1;
      #1 $finish;

  end

  initial begin
    $dumpfile("testbench_tb.vcd");
    $dumpvars(0, testbench);
  end

endmodule

Ejercicio_4/testbench_tb.vcd
$date
	Sat Oct 31 02:30:08 2020
$end
$version
	Icarus Verilog
$end
$timescale
	1ps
$end
$scope module testbench $end
$var wire 4 ! Y [3:0] $end
$var reg 4 " A [3:0] $end
$var reg 1 # enable $end
$scope module B1 $end
$var wire 4 $ A [3:0] $end
$var wire 1 # enable $end
$var wire 4 % Y [3:0] $end
$upscope $end
$upscope $end
$enddefinitions $end
#0
$dumpvars
bx %
bx $
x#
bx "
bx !
$end
#1
b10 !
b10 %
b10 "
b10 $
1#
#2
b1110 !
b1110 %
b1110 "
b1110 $
#3
b1111 !
b1111 %
b1111 "
b1111 $
#4
bz !
bz %
b1011 "
b1011 $
0#
#5
b1 !
b1 %
b1 "
b1 $
1#
#6
bz !
bz %
b1010 "
b1010 $
0#
#7
b101 !
b101 %
b101 "
b101 $
1#
#8
b1101 !
b1101 %
b1101 "
b1101 $
