Ejercicio_3/Ejercicio_3.v
/* Margareth Vela
Carné: 19458

Flip Flop tipo D de 1 bit */

module FF_D(input wire clock, reset, enable, d, output reg Y);
  always @ (posedge clock, posedge reset, posedge enable) begin
    if(reset) begin
      Y <= 1'b0;
    end
    else if (enable) begin
      Y <= d;
    end
  end
endmodule

//Flip Flop tipo JK de 1 bit

module FF_JK(input wire clock, reset, enable, J, K, output wire Q);
  wire w1, w2;

  FF_D G1(clock, reset, enable, QF, Q);

  and U1(w1, ~Q, J);
  and U2(w2, Q, ~K);
  or U3(QF, w1, w2);

endmodule

Ejercicio_3/testbench_tb.v
//Testbench ejercicio 3
module testbench();

  reg clk, rst, enable, J, K;
  wire Q;

  FF_JK G1(clk, rst, enable, J, K, Q);

  always
    begin
      clk <= 1;
      #1 clk <= ~clk;
      #1;
  end

  initial begin
  $display("\n");
    $display("Flip Flop Tipo JK - Ejercicio 3");
    $display("\n");
    $display(" Clk RST | EN  J  K |  Q    ");
    $display(" -------------------------- ");
    $monitor(" %b    %b  |  %b  %b  %b |   %b ", clk, rst, enable, J, K, Q);

    #1 rst = 1; //Reset inicial
    #1 rst = 0; enable = 1; J = 1; K = 0; //Reset inicial
    #2  J = 0; K = 1;
    #4 enable = 0;  J = 1; K = 0;
    #2  J = 0; K = 1;
    #2 enable = 1; J = 1; K = 1;
    #6  J = 0; K = 0;
    #2  J = 0; K = 1;
    #2  J = 0; K = 0;
    #3 $finish;

    end

  initial begin
        $dumpfile("testbench_tb.vcd");
        $dumpvars(0, testbench);
      end
endmodule

Ejercicio_3/testbench_tb.vcd
$date
	Sat Oct 31 02:09:06 2020
$end
$version
	Icarus Verilog
$end
$timescale
	1ps
$end
$scope module testbench $end
$var wire 1 ! Q $end
$var reg 1 " J $end
$var reg 1 # K $end
$var reg 1 $ clk $end
$var reg 1 % enable $end
$var reg 1 & rst $end
$scope module G1 $end
$var wire 1 " J $end
$var wire 1 # K $end
$var wire 1 ' QF $end
$var wire 1 $ clock $end
$var wire 1 % enable $end
$var wire 1 & reset $end
$var wire 1 ( w1 $end
$var wire 1 ) w2 $end
$var wire 1 ! Q $end
$scope module G1 $end
$var wire 1 $ clock $end
$var wire 1 ' d $end
$var wire 1 % enable $end
$var wire 1 & reset $end
$var reg 1 ! Y $end
$upscope $end
$upscope $end
$upscope $end
$enddefinitions $end
#0
$dumpvars
x)
x(
x'
x&
x%
1$
x#
x"
x!
$end
#1
0)
0!
0$
1&
#2
1)
1!
1$
1'
0(
0#
1"
1%
0&
#3
0$
#4
0!
1$
0'
0)
1#
0"
#5
0$
#6
1$
#7
0$
#8
1$
1'
1(
0#
1"
0%
#9
0$
#10
1$
0'
0(
1#
0"
#11
0$
#12
1!
1$
0'
0(
1"
1%
#13
0$
#14
1'
1(
0!
1$
#15
0$
#16
0'
0(
1!
1$
#17
0$
#18
1$
1'
1)
0#
0"
#19
0$
#20
0!
1$
0'
0)
1#
#21
0$
#22
1$
0#
